find_jcmwave/__init__.py
find_jcmwave/cli.py
find_jcmwave-1.0.2.dist-info/LICENSE
find_jcmwave-1.0.2.dist-info/METADATA
find_jcmwave-1.0.2.dist-info/WHEEL
find_jcmwave-1.0.2.dist-info/entry_points.txt
find_jcmwave-1.0.2.dist-info/top_level.txt
find_jcmwave-1.0.2.dist-info/RECORD
