Metadata-Version: 2.1
Name: find_jcmwave
Version: 1.0.2
Summary: Dynamically link jcmwave from JCMROOT into your environment
Author-email: Jan David Fischbach <mail@jan-dav.id>
License: MIT License
Keywords: jcm,jcmwave,fem
Requires-Python: >=3.9
License-File: LICENSE
Requires-Dist: numpy
Requires-Dist: requests
Requires-Dist: colorama
